{
  "ckks_params": {
    "N": 8192,
    "coeff_mod_bit_sizes": [
      60,
      40,
      60
    ],
    "scale_bits": 40,
    "k_shots": 1
  },
  "sigma_rec": 0.08014724403619766,
  "ci_method": "Student t at 95%, df=n-1",
  "t_critical_95": {
    "3": 4.303,
    "4": 3.182,
    "5": 2.776,
    "6": 2.571,
    "7": 2.447
  },
  "ours_full_hires": [
    {
      "acc1": 0.786,
      "acc10": 0.894,
      "acc10_stage1_hnsw": 0.894,
      "mrr": 0.8201579365079364,
      "ndcg10": 0.8378855740408828,
      "pearson_mean": 0.9999999999318188,
      "kendall_mean": 0.9993939393939394,
      "rerank_per_query_ms": 129.84995079040527
    },
    {
      "acc1": 0.784,
      "acc10": 0.892,
      "acc10_stage1_hnsw": 0.892,
      "mrr": 0.8181579365079364,
      "ndcg10": 0.8358855740408828,
      "pearson_mean": 0.9999999999413519,
      "kendall_mean": 0.9998479065379547,
      "rerank_per_query_ms": 129.59637069702148
    },
    {
      "acc1": 0.784,
      "acc10": 0.89,
      "acc10_stage1_hnsw": 0.89,
      "mrr": 0.8174912698412697,
      "ndcg10": 0.8348855740408828,
      "pearson_mean": 0.9999999999382773,
      "kendall_mean": 0.9992418459318942,
      "rerank_per_query_ms": 126.79217624664307
    },
    {
      "acc1": 0.784,
      "acc10": 0.892,
      "acc10_stage1_hnsw": 0.892,
      "mrr": 0.8181579365079364,
      "ndcg10": 0.8358855740408828,
      "pearson_mean": 0.9999999999508676,
      "kendall_mean": 0.9987878787878788,
      "rerank_per_query_ms": 129.4469132423401
    },
    {
      "acc1": 0.784,
      "acc10": 0.892,
      "acc10_stage1_hnsw": 0.892,
      "mrr": 0.8184912698412697,
      "ndcg10": 0.8361474335480258,
      "pearson_mean": 0.9999999999246164,
      "kendall_mean": 0.9996958130759097,
      "rerank_per_query_ms": 127.29731845855713
    }
  ],
  "aggregate": {
    "acc1": {
      "mean": 0.7844,
      "std": 0.0008944271909999166,
      "t95_half": 0.0011104000000000008
    },
    "acc10": {
      "mean": 0.892,
      "std": 0.0014142135623730963,
      "t95_half": 0.0017556965569254855
    },
    "mrr": {
      "mean": 0.8184912698412697,
      "std": 0.0010000000000000102,
      "t95_half": 0.0012414649411078957
    },
    "ndcg10": {
      "mean": 0.8361379459423114,
      "std": 0.0010897376425461024,
      "t95_half": 0.0013528710782265403
    },
    "rerank_per_query_ms": {
      "mean": 128.5965458869934,
      "std": 1.4350557351112763,
      "t95_half": 1.7815713836764506
    }
  }
}